seamless_entropy/__init__.py
seamless_entropy/helpers.py
seamless_entropy/pure_python.py
seamless_entropy/use_scipy.py
entropy_c.cp310-win_amd64.pyd
seamless_entropy-0.2.6.dist-info/METADATA
seamless_entropy-0.2.6.dist-info/WHEEL
seamless_entropy-0.2.6.dist-info/RECORD
